[{"name":"vc.builder.install","duration":871743,"timestamp":86719401788,"id":"f4c2a487-67de-4a82-b643-7cc5729f6aec","parentId":"ed1a63b7-a7f9-49d9-b2fc-3ab0efd1b54d","tags":{"cliType":"npm","lockfileVersion":"3"},"startTime":1772522202822},{"name":"vc.builder.build","duration":28358598,"timestamp":86720274464,"id":"ca7830b3-c2d6-4b7c-ae30-9423d98ed69e","parentId":"ed1a63b7-a7f9-49d9-b2fc-3ab0efd1b54d","tags":{"buildScriptName":"build"},"startTime":1772522203694},{"name":"vc.builder","duration":30090453,"timestamp":86719382886,"id":"ed1a63b7-a7f9-49d9-b2fc-3ab0efd1b54d","parentId":"bee5eaba-8113-4bd9-924d-19c2023c9465","tags":{"builder.name":"@vercel/next","builder.version":"4.15.37","builder.dynamicallyInstalled":"false","install":"true","build":"true"},"startTime":1772522202803},{"name":"vc.builder.diagnostics","duration":1248,"timestamp":86749473442,"id":"4fc841c1-0cfe-4641-85de-451b3455f4fb","parentId":"ed1a63b7-a7f9-49d9-b2fc-3ab0efd1b54d","tags":{},"startTime":1772522232893},{"name":"vc.builder.writeBuildResult","duration":118723,"timestamp":86749474802,"id":"1b84ad4a-42e2-4483-96c1-ee0477d1d17a","parentId":"ed1a63b7-a7f9-49d9-b2fc-3ab0efd1b54d","tags":{"buildOutputLength":"1"},"startTime":1772522232895},{"name":"vc.doBuild","duration":30346948,"timestamp":86719260693,"id":"bee5eaba-8113-4bd9-924d-19c2023c9465","parentId":"f8f6d64d-ec54-4523-bf5c-714a94fb9785","tags":{},"startTime":1772522202681},{"name":"vc","duration":30359084,"timestamp":86719248569,"id":"f8f6d64d-ec54-4523-bf5c-714a94fb9785","tags":{},"startTime":1772522202668}]